cloudmesh_cmd3light/__init__.py
cloudmesh_cmd3light/cm.py
cloudmesh_cmd3light/command.py
cloudmesh_cmd3light/console.py
cloudmesh_cmd3light/version.py
cloudmesh_cmd3light/plugins/__init__.py
cloudmesh_cmd3light/plugins/Bar.py
cloudmesh_cmd3light/plugins/CommandsCommands.py
cloudmesh_cmd3light/plugins/ManCommand.py
cloudmesh_cmd3light/plugins/OpenCommand.py
cloudmesh_cmd3light/plugins/SecureShellCommand.py
cloudmesh_cmd3light/plugins/TerminalCommands.py
cloudmesh_cmd3light-1.0.0.dist-info/DESCRIPTION.rst
cloudmesh_cmd3light-1.0.0.dist-info/entry_points.txt
cloudmesh_cmd3light-1.0.0.dist-info/METADATA
cloudmesh_cmd3light-1.0.0.dist-info/metadata.json
cloudmesh_cmd3light-1.0.0.dist-info/RECORD
cloudmesh_cmd3light-1.0.0.dist-info/top_level.txt
cloudmesh_cmd3light-1.0.0.dist-info/WHEEL
