Metadata-Version: 2.0
Name: cloudmesh-cmd3light
Version: 1.0.0
Summary: cloudmesh_cmd3light - A dynamic CMD shell with plugins
Home-page: https://github.com/cloudmesh/cloudmesh_cmd3light
Author: Gregor von Laszewski
Author-email: laszewski@gmail.com
License: Apache License, Version 2.0
Keywords: cloud cmd commandshell plugins
Platform: UNKNOWN
Classifier: Intended Audience :: Developers
Classifier: Intended Audience :: Education
Classifier: Intended Audience :: Science/Research
Classifier: Development Status :: 5 - Production/Stable
Classifier: Intended Audience :: Developers
Classifier: License :: OSI Approved :: Apache Software License
Classifier: Operating System :: MacOS :: MacOS X
Classifier: Operating System :: POSIX :: Linux
Classifier: Programming Language :: Python :: 2.7
Classifier: Topic :: Scientific/Engineering
Classifier: Topic :: System :: Clustering
Classifier: Topic :: System :: Distributed Computing
Classifier: Topic :: Software Development :: Libraries :: Python Modules
Classifier: Environment :: Console
Requires-Dist: pyreadline (<=1.7.1.dev-r0)
Requires-Dist: colorama
Requires-Dist: cloudmesh-base
Requires-Dist: future
Requires-Dist: docopt
Requires-Dist: pyaml
Requires-Dist: simplejson
Requires-Dist: python-hostlist
Requires-Dist: prettytable
Requires-Dist: sqlalchemy
Requires-Dist: urllib3
Requires-Dist: requests
Requires-Dist: sandman
Requires-Dist: gitchangelog
Requires-Dist: six
